tests/manifold/__init__.py
tests/manifold/test_stuff.py
tests/symplectic/__init__.py
tests/symplectic/test_stuff.py
tests/symplectic_integration/__init__.py
tests/symplectic_integration/hamiltons_equations.py
tests/symplectic_integration/kepler_nd.py
tests/symplectic_integration/pendulum_nd.py
tests/symplectic_integration/results.py
tests/symplectic_integration/test_nonseparable_hamiltonian.py
tests/symplectic_integration/test_separable_hamiltonian.py
vorpy/__init__.py
vorpy/apply_along_axes.py
vorpy/index_map.py
vorpy/linalg.py
vorpy/pickle.py
vorpy/symbolic.py
vorpy/tensor.py
vorpy/experimental/J_vs_lambda.py
vorpy/experimental/__init__.py
vorpy/experimental/bernstein.py
vorpy/experimental/bezier.py
vorpy/experimental/coordinates.py
vorpy/experimental/integrate_tangent_flow.py
vorpy/experimental/kepler_r_inv_sq.py
vorpy/experimental/magnetic.py
vorpy/experimental/plot.py
vorpy/experimental/require.py
vorpy/integration/__init__.py
vorpy/integration/adaptive.py
vorpy/integration/rungekutta.py
vorpy/manifold/__init__.py
vorpy/realfunction/__init__.py
vorpy/realfunction/bernstein.py
vorpy/realfunction/bezier.py
vorpy/realfunction/piecewiselinear.py
vorpy/riemannian/__init__.py
vorpy/symplectic/__init__.py
vorpy/symplectic_integration/__init__.py
vorpy/symplectic_integration/exceptions.py
vorpy/symplectic_integration/nonseparable_hamiltonian.py
vorpy/symplectic_integration/separable_hamiltonian.py
vorpy-0.9.0.dist-info/LICENSE
vorpy-0.9.0.dist-info/METADATA
vorpy-0.9.0.dist-info/WHEEL
vorpy-0.9.0.dist-info/top_level.txt
vorpy-0.9.0.dist-info/RECORD
