Metadata-Version: 2.1
Name: vorpy
Version: 0.9.0
Summary: VictOR dods' PYthon package (mostly math-related)
Home-page: https://github.com/vdods/vorpy
Author: Victor Dods
Author-email: victor.dods@gmail.com
License: MIT License
Download-URL: https://github.com/vdods/vorpy/archive/v0.9.0.tar.gz
Keywords: numerical computation symbolic tensor calculus cached lambdify geometric symplectic integration
Platform: UNKNOWN
Requires-Python: >=3.6
Requires-Dist: dill
Requires-Dist: numpy
Requires-Dist: sympy
